entangle/__init__.py
entangle/__version__.py
entangle/__version_tmpl__.py
entangle/aws.py
entangle/batch.py
entangle/containers.py
entangle/dataflow.py
entangle/gpu.py
entangle/http.py
entangle/importer.py
entangle/process.py
entangle/scheduler.py
entangle/ssh.py
entangle/thread.py
entangle/workflow.py
entangle/examples/aiexample.py
entangle/examples/dataflowexample.py
entangle/examples/dataflowexample2.py
entangle/examples/dockerexample.py
entangle/examples/example.py
entangle/examples/example2.py
entangle/examples/example3.py
entangle/examples/example4.py
entangle/examples/example5.py
entangle/examples/example6.py
entangle/examples/example_graph.py
entangle/examples/example_graph_future.py
entangle/examples/example_with_future.py
entangle/examples/lambdaexample.py
entangle/examples/listexample.py
entangle/examples/listexample2.py
entangle/examples/retry_example.py
entangle/examples/schedulerexample.py
entangle/examples/schedulerexample2.py
entangle/examples/sshdataflowexample.py
entangle/examples/sshschedulerexample.py
entangle/examples/timeoutexample.py
entangle/logging/__init__.py
entangle/logging/debug.py
entangle/logging/file.py
entangle/logging/info.py
entangle/tests/__init__.py
entangle/tests/conftest.py
entangle/tests/test_entangle.py
entangle/tests/test_gpu_entangle.py
py_entangle-0.2.3.dist-info/LICENSE
py_entangle-0.2.3.dist-info/METADATA
py_entangle-0.2.3.dist-info/WHEEL
py_entangle-0.2.3.dist-info/top_level.txt
py_entangle-0.2.3.dist-info/RECORD
