Metadata-Version: 2.1
Name: py-entangle
Version: 0.2.3
Summary: A python native parallel processing framework based on simple decorators.
Home-page: https://github.com/radiantone/entangle
Author: Darren Govoni
Author-email: darren@ontrenet.com
License: MIT
Keywords: parallel processing,devops,dataflow,supercomputing,workflows
Platform: UNKNOWN
Classifier: Development Status :: 2 - Pre-Alpha
Classifier: Intended Audience :: Developers
Classifier: Programming Language :: Python :: 3.8
Requires-Python: ==3.8.*
License-File: LICENSE
Requires-Dist: scp (==0.13.3)
Requires-Dist: astunparse (==1.6.3)
Requires-Dist: async-timeout (==3.0.1)
Requires-Dist: cachetools (==4.2.1)
Requires-Dist: certifi (==2020.12.5)
Requires-Dist: cffi (==1.14.3)
Requires-Dist: cryptography (==3.2.1)
Requires-Dist: dill (==0.3.3)
Requires-Dist: docker (==5.0.0)
Requires-Dist: filelock (==3.0.12)
Requires-Dist: gast (==0.4.0)
Requires-Dist: globus-sdk (==2.0.1)
Requires-Dist: numpy (==1.19.2)
Requires-Dist: paramiko (==2.7.2)
Requires-Dist: pip
Requires-Dist: psutil (==5.8.0)
Requires-Dist: py-cpuinfo (==8.0.0)
Requires-Dist: pytest (==6.2.4)
Requires-Dist: requests (==2.24.0)
Requires-Dist: scipy (==1.6.2)
Requires-Dist: setuptools
Requires-Dist: six (==1.15.0)
Requires-Dist: typeguard (==2.12.0)
Requires-Dist: pylint (==2.8.2)
